resset/__config.py
resset/__init__.py
resset/secret.py
resset/ziputils.py
resset/report/__init__.py
resset/report/reportdata.py
resset-0.9.7.dist-info/METADATA
resset-0.9.7.dist-info/WHEEL
resset-0.9.7.dist-info/top_level.txt
resset-0.9.7.dist-info/RECORD
