Metadata-Version: 2.1
Name: resset
Version: 0.9.7
Summary: A small example package
Home-page: UNKNOWN
Author: zhangq
Author-email: 569535175@qq.com
License: UNKNOWN
Platform: UNKNOWN
Requires-Dist: pandas
Requires-Dist: pymssql
Requires-Dist: SQLAlchemy
Requires-Dist: pycryptodome
